aws_secretsmanager_caching/__init__.py
aws_secretsmanager_caching/config.py
aws_secretsmanager_caching/decorators.py
aws_secretsmanager_caching/secret_cache.py
aws_secretsmanager_caching/cache/__init__.py
aws_secretsmanager_caching/cache/items.py
aws_secretsmanager_caching/cache/lru.py
aws_secretsmanager_caching/cache/secret_cache_hook.py
aws_secretsmanager_caching-1.1.1.5.dist-info/LICENSE
aws_secretsmanager_caching-1.1.1.5.dist-info/METADATA
aws_secretsmanager_caching-1.1.1.5.dist-info/WHEEL
aws_secretsmanager_caching-1.1.1.5.dist-info/top_level.txt
aws_secretsmanager_caching-1.1.1.5.dist-info/RECORD
