Metadata-Version: 2.1
Name: aws-secretsmanager-caching
Version: 1.1.1.5
Summary: Client-side AWS Secrets Manager caching library
Home-page: https://github.com/aws/aws-secretsmanager-caching-python
Author: Amazon Web Services
Author-email: aws-secretsmanager-dev@amazon.com
License: UNKNOWN
Keywords: secretsmanager secrets manager development cache caching client
Platform: UNKNOWN
Classifier: Development Status :: 5 - Production/Stable
Classifier: Intended Audience :: Developers
Classifier: License :: OSI Approved :: Apache Software License
Classifier: Programming Language :: Python :: 3.6
Classifier: Programming Language :: Python :: 3.7
Requires-Python: >3.5
